{
  "project_info": {
    "project_number": "400271469660",
    "project_id": "river-pointer-129523"
  },
  "client": [
    {
      "client_info": {
        "mobilesdk_app_id": "1:400271469660:android:40bd9973174263d2",
        "android_client_info": {
          "package_name": "com.example.agneev.gcm_test"
        }
      },
      "oauth_client": [],
      "api_key": [
        {
          "current_key": "AIzaSyBm6Z7a25GI3lelFhhCdgQlTUxPI-mIMII"
        }
      ],
      "services": {
        "analytics_service": {
          "status": 1
        },
        "appinvite_service": {
          "status": 1,
          "other_platform_oauth_client": []
        },
        "ads_service": {
          "status": 1
        }
      }
    }
  ],
  "configuration_version": "1"
}